anicli/__init__.py
anicli/_completion.py
anicli/_validator.py
anicli/check_updates.py
anicli/cli_utlis.py
anicli/cookies.py
anicli/headers.py
anicli/log.py
anicli/updater.py
anicli/utils.py
anicli/views.py
anicli/cli/__init__.py
anicli/cli/compat.py
anicli/cli/config.py
anicli/cli/events.py
anicli/cli/ongoing.py
anicli/cli/player.py
anicli/cli/search.py
anicli/cli/slice_play.py
anicli/cli/video_utils.py
anicli_ru-5.0.17.dist-info/METADATA
anicli_ru-5.0.17.dist-info/WHEEL
anicli_ru-5.0.17.dist-info/entry_points.txt
anicli_ru-5.0.17.dist-info/licenses/LICENSE
anicli_ru-5.0.17.dist-info/RECORD
