Metadata-Version: 2.4
Name: anicli-ru
Version: 5.0.17
Summary: cli tool for watching anime
Project-URL: Documentation, https://github.com/vypivshiy/ani-cli-ru#readme
Project-URL: Issues, https://github.com/vypivshiy/ani-cli-ru/issues
Project-URL: Source, https://github.com/vypivshiy/ani-cli-ru
Author: vypivshiy
License-Expression: MIT
License-File: LICENSE
Classifier: Development Status :: 4 - Beta
Classifier: Programming Language :: Python
Classifier: Programming Language :: Python :: 3.8
Classifier: Programming Language :: Python :: 3.9
Classifier: Programming Language :: Python :: 3.10
Classifier: Programming Language :: Python :: 3.11
Classifier: Programming Language :: Python :: 3.12
Classifier: Programming Language :: Python :: 3.13
Classifier: Programming Language :: Python :: Implementation :: CPython
Requires-Python: >=3.8
Requires-Dist: anicli-api>=0.7.14
Requires-Dist: eggella>=0.1.7
Requires-Dist: tqdm>=4.67.1
Provides-Extra: browser-cookies
Requires-Dist: anicli-api[browser-cookies]; extra == 'browser-cookies'
Provides-Extra: dev
Requires-Dist: mypy>=1.14.1; extra == 'dev'
Requires-Dist: ruff>=0.9.9; extra == 'dev'
